modules/__init__.py
modules/functions.py
modules/tabulate.py
modules/texttable.py
lazy_network_engineer_jaaacck-0.1a0.dist-info/LICENSE
lazy_network_engineer_jaaacck-0.1a0.dist-info/METADATA
lazy_network_engineer_jaaacck-0.1a0.dist-info/WHEEL
lazy_network_engineer_jaaacck-0.1a0.dist-info/top_level.txt
lazy_network_engineer_jaaacck-0.1a0.dist-info/RECORD
