Metadata-Version: 2.1
Name: lazy-network-engineer-jaaacck
Version: 0.1a0
Summary: Lots of scripts and APIs bundled together in one easy to use CLI
Home-page: https://github.com/jaaacck/lazy-network-engineer
Author: Jack Houlden
Author-email: xjackh@gmail.com
License: UNKNOWN
Platform: UNKNOWN
Classifier: Programming Language :: Python :: 3
Classifier: License :: OSI Approved :: MIT License
Classifier: Operating System :: OS Independent
Requires-Python: >=3.5.2
